passsafe/__init__.py
passsafe-1.5.dist-info/License.txt
passsafe-1.5.dist-info/METADATA
passsafe-1.5.dist-info/WHEEL
passsafe-1.5.dist-info/top_level.txt
passsafe-1.5.dist-info/RECORD
