Metadata-Version: 2.1
Name: passsafe
Version: 1.5
Summary: For making passwords safe and memorable!
Home-page: UNKNOWN
Author: Advay
Author-email: catch149@gmail.com
License: UNKNOWN
Platform: UNKNOWN
Classifier: Programming Language :: Python :: 3
Classifier: License :: OSI Approved :: MIT License
Classifier: Operating System :: OS Independent
License-File: License.txt
